wsaccel/__init__.py
wsaccel/dfa.h
wsaccel/utf8validator.c
wsaccel/utf8validator.cp310-win_amd64.pyd
wsaccel/xormask.c
wsaccel/xormask.cp310-win_amd64.pyd
wsaccel-0.6.7.dist-info/LICENSE
wsaccel-0.6.7.dist-info/METADATA
wsaccel-0.6.7.dist-info/WHEEL
wsaccel-0.6.7.dist-info/top_level.txt
wsaccel-0.6.7.dist-info/RECORD
