Metadata-Version: 2.1
Name: wsaccel
Version: 0.6.7
Summary: Accelerator for ws4py and AutobahnPython
Author-email: Inada Naoki <songofacandy@gmail.com>
License: Apache 2.0
Project-URL: Website, https://github.com/methane/wsaccel
Classifier: Intended Audience :: Developers
Classifier: Operating System :: OS Independent
Classifier: Programming Language :: Python
Classifier: Programming Language :: Python :: 3
Classifier: Programming Language :: Python :: 3.9
Classifier: Programming Language :: Python :: 3.10
Classifier: Programming Language :: Python :: 3.11
Classifier: Programming Language :: Python :: 3.12
Classifier: Programming Language :: Python :: 3.13
Classifier: Programming Language :: Python :: Implementation :: CPython
Requires-Python: >=3.9
License-File: LICENSE
